tiktok_captcha/__init__.py
tiktok_captcha/exceptions.py
tiktok_captcha/py.typed
tiktok_captcha/schemas.py
tiktok_captcha/solver.py
tiktok_captcha-0.1.1.dist-info/licenses/LICENSE
tiktok_captcha-0.1.1.dist-info/METADATA
tiktok_captcha-0.1.1.dist-info/WHEEL
tiktok_captcha-0.1.1.dist-info/top_level.txt
tiktok_captcha-0.1.1.dist-info/RECORD
