Metadata-Version: 2.4
Name: tiktok-captcha
Version: 0.1.1
Summary: TikTok Captcha Solver API (puzzle, whirl, 3d, end-to-end verification)
Author-email: Just Scrape <just.scrape.dev@gmail.com>
Maintainer-email: Just Scrape <just.scrape.dev@gmail.com>
License: MIT
Project-URL: Documentation, https://github.com/justscrapeme/tiktok-captcha-solver
Project-URL: Issues, https://github.com/justscrapeme/tiktok-captcha-solver/issues
Project-URL: Source, https://github.com/justscrapeme/tiktok-captcha-solver
Classifier: Development Status :: 4 - Beta
Classifier: Environment :: Web Environment
Classifier: Framework :: AsyncIO
Classifier: Intended Audience :: Developers
Classifier: License :: OSI Approved :: MIT License
Classifier: Operating System :: OS Independent
Classifier: Programming Language :: Python :: 3
Classifier: Programming Language :: Python :: 3.10
Classifier: Programming Language :: Python :: 3.11
Classifier: Programming Language :: Python :: 3.12
Classifier: Programming Language :: Python :: 3.13
Classifier: Programming Language :: Python :: Implementation :: CPython
Classifier: Topic :: Internet :: WWW/HTTP
Classifier: Topic :: Internet :: WWW/HTTP :: HTTP Servers
Classifier: Topic :: Software Development :: Libraries :: Python Modules
Classifier: Typing :: Typed
Requires-Python: >=3.10
License-File: LICENSE
Requires-Dist: aiohttp>=3.12.15
Requires-Dist: pydantic>=2.11.7
Dynamic: license-file
